mfunc/__init__.py
mfunc/mfunc.py
mfunc-0.1.1.dist-info/METADATA
mfunc-0.1.1.dist-info/WHEEL
mfunc-0.1.1.dist-info/licenses/LICENSE
mfunc-0.1.1.dist-info/RECORD
