Metadata-Version: 2.1
Name: mfunc
Version: 0.1.1
Summary: A python library to add list slicing capabilities and equality checking to mathematical functions.
Project-URL: Homepage, https://github.com/PlaceReporter99/mfunc-bug-tracker
Project-URL: Bug Tracker, https://github.com/PlaceReporter99/mfunc-bug-tracker/issues
Author-email: PlaceReporter99 <sfurman35@outlook.com>
License-File: LICENSE
Classifier: License :: OSI Approved :: MIT License
Classifier: Operating System :: OS Independent
Classifier: Programming Language :: Python :: 3
Requires-Python: >=3.7
